pyscriptnative.py
pyscriptnative-0.3.2.data/scripts/pyscriptnative.py
pyscriptnative-0.3.2.dist-info/METADATA
pyscriptnative-0.3.2.dist-info/WHEEL
pyscriptnative-0.3.2.dist-info/top_level.txt
pyscriptnative-0.3.2.dist-info/RECORD
