Metadata-Version: 2.1
Name: pyscriptnative
Version: 0.3.2
Summary: pyscriptnative brings the support for Python scripting on the web of py-script in Flask.
Home-page: https://github.com/AquaQuokka/pyscriptnative
Author: AquaQuokka
License: BSD-3-Clause
Requires-Dist: flask
Requires-Dist: jinja2
